Workbook

Sheet Mission 1 - Question 2
G2: Hypothèse 1
D3: Investissement | E3: Exploitation | H3: N | I3: N+1 | J3: N+2 | K3: N+3 | L3: N+4 | M3: N+5
A4: Création société | B4: 1000 | D4: 1000 | G4: Ventes | I4: 150 | J4: 200 | K4: 300 | L4: 300 | M4: 300
A5: Création site Prestashop | B5: 15000 | D5: 15000
A6: Infogérance du site | B6: 500,00 € par an | E6: 500 | G6: Investissement | H6: -17000
A7: hébergement du site | B7: 200,00 € par an | E7: 200 | G7: CA | I7: =I4*350 -> 52500 | J7: =J4*350 -> 70000 | K7: =K4*350 -> 105000 | L7: =L4*350 -> 105000 | M7: =M4*350 -> 105000
A8: Salaire Viktoria | B8: 25 000,00 € annuels, charges sociales comprises | E8: 25000 | G8: Coût des produits | I8: =I4*100 -> 15000 | J8: =J4*100 -> 20000 | K8: =K4*100 -> 30000 | L8: =L4*100 -> 30000 | M8: =M4*100 -> 30000
A9: SEO | B9: 1 000,00 € par an | E9: 1000 | G9: Expédition | I9: =5*I4 -> 750 | J9: =5*J4 -> 1000 | K9: =5*K4 -> 1500 | L9: =5*L4 -> 1500 | M9: =5*M4 -> 1500
A10: SEA | B10: 6 000,00 € annuels | E10: 6000 | G10: Autres charges | I10: =SUM($E6:$E12) -> 50700 | J10: =SUM($E6:$E12) -> 50700 | K10: =SUM($E6:$E12) -> 50700 | L10: =SUM($E6:$E12) -> 50700 | M10: =SUM($E6:$E12) -> 50700
A11: Stocks de départ | B11: 1 000,00 € pour le fond de roulement | D11: 1000 | G11: Cash flows | H11: =H6 -> -17000 | I11: =I7-I8-I9-I10 -> -13950 | J11: =J7-J8-J9-J10 -> -1700 | K11: =K7-K8-K9-K10 -> 22800 | L11: =L7-L8-L9-L10 -> 22800 | M11: =M7-M8-M9-M10 -> 22800
A12: Loyer | B12: 1 500,00 € par mois | E12: =1500*12 -> 18000
A13: Coût des produits | B13: 100 € par pull | E13: 100 N | G13: Hypothèse 2
A14: Coûts logistiques expédition pulls | B14: 5,00 € par pull | E14: 5 N | H14: N | I14: N+1 | J14: N+2 | K14: N+3 | L14: N+4 | M14: N+5
D15: =SUM(D4:D14) -> 17000 | E15: =SUM(E6:E12) -> 50700 | G15: Ventes | I15: 300 | J15: 300 | K15: 300 | L15: 300 | M15: 300
G17: Investissement | H17: -17000
G18: CA | I18: =I15*350 -> 105000 | J18: =J15*350 -> 105000 | K18: =K15*350 -> 105000 | L18: =L15*350 -> 105000 | M18: =M15*350 -> 105000
G19: Coût des produits | I19: =I15*100 -> 30000 | J19: =J15*100 -> 30000 | K19: =K15*100 -> 30000 | L19: =L15*100 -> 30000 | M19: =M15*100 -> 30000
G20: Expédition | I20: =5*I15 -> 1500 | J20: =5*J15 -> 1500 | K20: =5*K15 -> 1500 | L20: =5*L15 -> 1500 | M20: =5*M15 -> 1500
G21: Autres charges | I21: =SUM($E6:$E12) -> 50700 | J21: =SUM($E6:$E12) -> 50700 | K21: =SUM($E6:$E12) -> 50700 | L21: =SUM($E6:$E12) -> 50700 | M21: =SUM($E6:$E12) -> 50700
G22: Cash flows | H22: =H17 -> -17000 | I22: =I18-I19-I20-I21 -> 22800 | J22: =J18-J19-J20-J21 -> 22800 | K22: =K18-K19-K20-K21 -> 22800 | L22: =L18-L19-L20-L21 -> 22800 | M22: =M18-M19-M20-M21 -> 22800
F26: 0.1

Sheet Mission 2 - Question 3
A6: Actualisation Hypothèse 1
B7: 0 | C7: 1 | D7: 2 | E7: 3 | F7: 4 | G7: 5
A8: ='Mission 1 - Question 2'!G11 -> Cash flows | B8: ='Mission 1 - Question 2'!H11 -> -17000 | C8: ='Mission 1 - Question 2'!I11 -> -13950 | D8: ='Mission 1 - Question 2'!J11 -> -1700 | E8: ='Mission 1 - Question 2'!K11 -> 22800 | F8: ='Mission 1 - Question 2'!L11 -> 22800 | G8: ='Mission 1 - Question 2'!M11 -> 22800
A9: Cash flows actualisés | B9: =B8*POWER(1+'Mission 1 - Question 2'!$F$26,-B7) -> -17000 | C9: =C8*POWER(1.1,-C7) -> -12681.818 | D9: =D8*POWER(1.1,-D7) -> -1404.9587 | E9: =E8*POWER(1.1,-E7) -> 17129.977 | F9: =F8*POWER(1.1,-F7) -> 15572.707 | G9: =G8*POWER(1.1,-G7) -> 14157.006 | I9: =SUM(B9:G9) -> 15772.914
A11: Actualisation Hypothèse 1
B12: 0 | C12: 1 | D12: 2 | E12: 3 | F12: 4 | G12: 5
A13: ='Mission 1 - Question 2'!G22 -> Cash flows | B13: ='Mission 1 - Question 2'!H22 -> -17000 | C13: ='Mission 1 - Question 2'!I22 -> 22800 | D13: ='Mission 1 - Question 2'!J22 -> 22800 | E13: ='Mission 1 - Question 2'!K22 -> 22800 | F13: ='Mission 1 - Question 2'!L22 -> 22800 | G13: ='Mission 1 - Question 2'!M22 -> 22800
A14: Cash flows actualisés | B14: =B13*POWER(1+'Mission 1 - Question 2'!$F$26,-B12) -> -17000 | C14: =C13*POWER(1.1,-C12) -> 20727.273 | D14: =D13*POWER(1.1,-D12) -> 18842.975 | E14: =E13*POWER(1.1,-E12) -> 17129.977 | F14: =F13*POWER(1.1,-F12) -> 15572.707 | G14: =G13*POWER(1.1,-G12) -> 14157.006 | I14: =SUM(B14:G14) -> 69429.938
B17: =B14 -> -17000 | C17: =C13 -> 22800 | D17: 3.7908 | I17: =B17+(C17*D17) -> 69430.24

Sheet Mission 3 - Question 4
C2: Actualisation Hypothèse 1
D3: 0 | E3: 1 | F3: 2 | G3: 3 | H3: 4 | I3: 5
A4: Création société | B4: 1000 | C4: Cash flows | D4: ='Mission 2 - Question 3'!B8 -> -17000 | E4: ='Mission 2 - Question 3'!C8 -> -13950 | F4: ='Mission 2 - Question 3'!D8 -> -1700 | G4: ='Mission 2 - Question 3'!E8 -> 22800 | H4: ='Mission 2 - Question 3'!F8 -> 22800 | I4: ='Mission 2 - Question 3'!G8 -> 22800
A5: Création site Prestashop | B5: 15000 | C5: Cash flows actualisés | D5: ='Mission 2 - Question 3'!B9 -> -17000 | E5: ='Mission 2 - Question 3'!C9 -> -12681.818 | F5: ='Mission 2 - Question 3'!D9 -> -1404.9587 | G5: ='Mission 2 - Question 3'!E9 -> 17129.977 | H5: ='Mission 2 - Question 3'!F9 -> 15572.707 | I5: ='Mission 2 - Question 3'!G9 -> 14157.006 | K5: =SUM(D5:I5) -> 15772.914 | L5: =K5/D4 -> -0.92781844
A6: Infogérance du site | B6: 500,00 € par an
A7: hébergement du site | B7: 200,00 € par an | C7: Actualisation Hypothèse 1
A8: Salaire Viktoria | B8: 25 000,00 € annuels, charges sociales comprises | D8: 0 | E8: 1 | F8: 2 | G8: 3 | H8: 4 | I8: 5
A9: SEO | B9: 1 000,00 € par an | C9: Cash flows | D9: ='Mission 2 - Question 3'!B13 -> -17000 | E9: ='Mission 2 - Question 3'!C13 -> 22800 | F9: ='Mission 2 - Question 3'!D13 -> 22800 | G9: ='Mission 2 - Question 3'!E13 -> 22800 | H9: ='Mission 2 - Question 3'!F13 -> 22800 | I9: ='Mission 2 - Question 3'!G13 -> 22800
A10: SEA | B10: 6 000,00 € annuels | C10: Cash flows actualisés | D10: ='Mission 2 - Question 3'!B14 -> -17000 | E10: ='Mission 2 - Question 3'!C14 -> 20727.273 | F10: ='Mission 2 - Question 3'!D14 -> 18842.975 | G10: ='Mission 2 - Question 3'!E14 -> 17129.977 | H10: ='Mission 2 - Question 3'!F14 -> 15572.707 | I10: ='Mission 2 - Question 3'!G14 -> 14157.006 | K10: =SUM(D10:I10) -> 69429.938 | L10: =K10/D9 -> -4.084114
A11: Stocks de départ | B11: 1 000,00 € pour le fond de roulement
A12: Loyer | B12: 1 500,00 € par mois
A13: Coût des produits | B13: 100 € par pull | D13: =D10 -> -17000 | E13: =E9 -> 22800 | F13: 3.7908 | K13: =D13+(E13*F13) -> 69430.24

Sheet Mission 3 - Question 5
A2: Hypothèse 1
B3: ='Mission 3 - Question 4'!D3 -> 0 | C3: ='Mission 3 - Question 4'!E3 -> 1 | D3: ='Mission 3 - Question 4'!F3 -> 2 | E3: ='Mission 3 - Question 4'!G3 -> 3 | F3: ='Mission 3 - Question 4'!H3 -> 4 | G3: ='Mission 3 - Question 4'!I3 -> 5
A4: ='Mission 3 - Question 4'!C4 -> Cash flows | B4: ='Mission 3 - Question 4'!D4 -> -17000 | C4: ='Mission 3 - Question 4'!E4 -> -13950 | D4: ='Mission 3 - Question 4'!F4 -> -1700 | E4: ='Mission 3 - Question 4'!G4 -> 22800 | F4: ='Mission 3 - Question 4'!H4 -> 22800 | G4: ='Mission 3 - Question 4'!I4 -> 22800
A5: ='Mission 3 - Question 4'!C5 -> Cash flows actualisés | B5: ='Mission 2 - Question 3'!B9 -> -17000 | C5: ='Mission 2 - Question 3'!C9 -> -12681.818 | D5: ='Mission 2 - Question 3'!D9 -> -1404.9587 | E5: ='Mission 2 - Question 3'!E9 -> 17129.977 | F5: ='Mission 2 - Question 3'!F9 -> 15572.707 | G5: ='Mission 2 - Question 3'!G9 -> 14157.006 | I5: =SUM(B5:G5) -> 15772.914
A6: Cash flows actualisés cumulés | B6: =B5 -> -17000 | C6: =C5+B6 -> -29681.818 | D6: =D5+C6 -> -31086.777 | E6: =E5+D6 -> -13956.799 | F6: =F5+E6 -> 1615.9074 | G6: =G5+F6 -> 15772.914
A8: Indice | B8: =I5/-B5 -> 0.92781844
A11: Hypothèse 2
B12: ='Mission 3 - Question 4'!D8 -> 0 | C12: ='Mission 3 - Question 4'!E8 -> 1 | D12: ='Mission 3 - Question 4'!F8 -> 2 | E12: ='Mission 3 - Question 4'!G8 -> 3 | F12: ='Mission 3 - Question 4'!H8 -> 4 | G12: ='Mission 3 - Question 4'!I8 -> 5
A13: ='Mission 3 - Question 4'!C9 -> Cash flows | B13: ='Mission 3 - Question 4'!D9 -> -17000 | C13: ='Mission 3 - Question 4'!E9 -> 22800 | D13: ='Mission 3 - Question 4'!F9 -> 22800 | E13: ='Mission 3 - Question 4'!G9 -> 22800 | F13: ='Mission 3 - Question 4'!H9 -> 22800 | G13: ='Mission 3 - Question 4'!I9 -> 22800
A14: ='Mission 3 - Question 4'!C10 -> Cash flows actualisés | B14: ='Mission 3 - Question 4'!D10 -> -17000 | C14: ='Mission 3 - Question 4'!E10 -> 20727.273 | D14: ='Mission 3 - Question 4'!F10 -> 18842.975 | E14: ='Mission 3 - Question 4'!G10 -> 17129.977 | F14: ='Mission 3 - Question 4'!H10 -> 15572.707 | G14: ='Mission 3 - Question 4'!I10 -> 14157.006 | I14: =SUM(B14:G14) -> 69429.938
A15: Cash flows actualisés cumulés | B15: =B14 -> -17000 | C15: =C14+B15 -> 3727.2727 | D15: =D14+C15 -> 22570.248 | E15: =E14+D15 -> 39700.225 | F15: =F14+E15 -> 55272.932 | G15: =G14+F15 -> 69429.938
A17: Indice | B17: =I14/-B14 -> 4.084114

Sheet Mission 4 - Question 6
A2: Taux 4 %
B3: 0 | C3: 1 | D3: 2 | E3: 3 | F3: 4 | G3: 5
A4: Cash flows | B4: ='Mission 1 - Question 2'!H11 -> -17000 | C4: ='Mission 1 - Question 2'!I11 -> -13950 | D4: ='Mission 1 - Question 2'!J11 -> -1700 | E4: ='Mission 1 - Question 2'!K11 -> 22800 | F4: ='Mission 1 - Question 2'!L11 -> 22800 | G4: ='Mission 1 - Question 2'!M11 -> 22800
A5: Cash flows actualisés | B5: =B4*POWER(1.04,-B3) -> -17000 | C5: =C4*POWER(1.04,-C3) -> -13413.462 | D5: =D4*POWER(1.04,-D3) -> -1571.7456 | E5: =E4*POWER(1.04,-E3) -> 20269.117 | F5: =F4*POWER(1.04,-F3) -> 19489.536 | G5: =G4*POWER(1.04,-G3) -> 18739.938 | I5: =SUM(B5:G5) -> 26513.383
A6: Cumul | B6: =B5 -> -17000 | C6: =C5+B6 -> -30413.462 | D6: =D5+C6 -> -31985.207 | E6: =E5+D6 -> -11716.09 | F6: =F5+E6 -> 7773.4454 | G6: =G5+F6 -> 26513.383
A8: Indice | B8: =I5/-B5 -> 1.5596108
A12: Taux 24 %
B13: 0 | C13: 1 | D13: 2 | E13: 3 | F13: 4 | G13: 5
A14: Cash flows | B14: =B4 -> -17000 | C14: =C4 -> -13950 | D14: =D4 -> -1700 | E14: =E4 -> 22800 | F14: =F4 -> 22800 | G14: =G4 -> 22800
A15: Cash flows actualisés | B15: =B14*POWER(1.24,-B13) -> -17000 | C15: =C14*POWER(1.24,-C13) -> -11250 | D15: =D14*POWER(1.24,-D13) -> -1105.6191 | E15: =E14*POWER(1.24,-E13) -> 11958.31 | F15: =F14*POWER(1.24,-F13) -> 9643.798 | G15: =G14*POWER(1.24,-G13) -> 7777.2565 | I15: =SUM(B15:G15) -> 23.744915
A16: Cumul | B16: =B15 -> -17000 | C16: =C15+B16 -> -28250 | D16: =D15+C16 -> -29355.619 | E16: =E15+D16 -> -17397.31 | F16: =F15+E16 -> -7753.5116 | G16: =G15+F16 -> 23.744915
A18: Indice | B18: =I15/-B15 -> 0.0013967597
